{
    "count": 20,
    "start": 0,
    "total": 73,
    "subjects": [
        {
            "rating": {
                "max": 10,
                "average": 0,
                "stars": "00",
                "min": 0
            },
            "genres": [
                "剧情",
                "奇幻"
            ],
            "title": "解忧杂货店",
            "casts": [
                {
                    "alt": "https://movie.douban.com/celebrity/1339594/",
                    "avatars": {
                        "small": "https://img3.doubanio.com/view/celebrity/s_ratio_celebrity/public/p1503377320.23.webp",
                        "large": "https://img3.doubanio.com/view/celebrity/s_ratio_celebrity/public/p1503377320.23.webp",
                        "medium": "https://img3.doubanio.com/view/celebrity/s_ratio_celebrity/public/p1503377320.23.webp"
                    },
                    "name": "王俊凯",
                    "id": "1339594"
                },
                {
                    "alt": "https://movie.douban.com/celebrity/1325127/",
                    "avatars": {
                        "small": "https://img1.doubanio.com/view/celebrity/s_ratio_celebrity/public/p1492095415.48.webp",
                        "large": "https://img1.doubanio.com/view/celebrity/s_ratio_celebrity/public/p1492095415.48.webp",
                        "medium": "https://img1.doubanio.com/view/celebrity/s_ratio_celebrity/public/p1492095415.48.webp"
                    },
                    "name": "迪丽热巴",
                    "id": "1325127"
                },
                {
                    "alt": "https://movie.douban.com/celebrity/1330472/",
                    "avatars": {
                        "small": "https://img3.doubanio.com/view/celebrity/s_ratio_celebrity/public/p1385100761.5.webp",
                        "large": "https://img3.doubanio.com/view/celebrity/s_ratio_celebrity/public/p1385100761.5.webp",
                        "medium": "https://img3.doubanio.com/view/celebrity/s_ratio_celebrity/public/p1385100761.5.webp"
                    },
                    "name": "董子健",
                    "id": "1330472"
                }
            ],
            "collect_count": 1379,
            "original_title": "解忧杂货店",
            "subtype": "movie",
            "directors": [
                {
                    "alt": "https://movie.douban.com/celebrity/1316056/",
                    "avatars": {
                        "small": "https://img1.doubanio.com/view/celebrity/s_ratio_celebrity/public/p34888.webp",
                        "large": "https://img1.doubanio.com/view/celebrity/s_ratio_celebrity/public/p34888.webp",
                        "medium": "https://img1.doubanio.com/view/celebrity/s_ratio_celebrity/public/p34888.webp"
                    },
                    "name": "韩杰",
                    "id": "1316056"
                }
            ],
            "year": "2017",
            "images": {
                "small": "https://img3.doubanio.com/view/photo/s_ratio_poster/public/p2503544593.webp",
                "large": "https://img3.doubanio.com/view/photo/s_ratio_poster/public/p2503544593.webp",
                "medium": "https://img3.doubanio.com/view/photo/s_ratio_poster/public/p2503544593.webp"
            },
            "alt": "https://movie.douban.com/subject/26654146/",
            "id": "26654146"
        },
        {
            "rating": {
                "max": 10,
                "average": 0,
                "stars": "00",
                "min": 0
            },
            "genres": [
                "喜剧"
            ],
            "title": "妖铃铃",
            "casts": [
                {
                    "alt": "https://movie.douban.com/celebrity/1127819/",
                    "avatars": {
                        "small": "https://img1.doubanio.com/view/celebrity/s_ratio_celebrity/public/p45539.webp",
                        "large": "https://img1.doubanio.com/view/celebrity/s_ratio_celebrity/public/p45539.webp",
                        "medium": "https://img1.doubanio.com/view/celebrity/s_ratio_celebrity/public/p45539.webp"
                    },
                    "name": "吴君如",
                    "id": "1127819"
                },
                {
                    "alt": "https://movie.douban.com/celebrity/1325700/",
                    "avatars": {
                        "small": "https://img1.doubanio.com/view/celebrity/s_ratio_celebrity/public/p1356510694.28.webp",
                        "large": "https://img1.doubanio.com/view/celebrity/s_ratio_celebrity/public/p1356510694.28.webp",
                        "medium": "https://img1.doubanio.com/view/celebrity/s_ratio_celebrity/public/p1356510694.28.webp"
                    },
                    "name": "沈腾",
                    "id": "1325700"
                },
                {
                    "alt": "https://movie.douban.com/celebrity/1317663/",
                    "avatars": {
                        "small": "https://img3.doubanio.com/view/celebrity/s_ratio_celebrity/public/p40756.webp",
                        "large": "https://img3.doubanio.com/view/celebrity/s_ratio_celebrity/public/p40756.webp",
                        "medium": "https://img3.doubanio.com/view/celebrity/s_ratio_celebrity/public/p40756.webp"
                    },
                    "name": "岳云鹏",
                    "id": "1317663"
                }
            ],
            "collect_count": 423,
            "original_title": "妖铃铃",
            "subtype": "movie",
            "directors": [
                {
                    "alt": "https://movie.douban.com/celebrity/1127819/",
                    "avatars": {
                        "small": "https://img1.doubanio.com/view/celebrity/s_ratio_celebrity/public/p45539.webp",
                        "large": "https://img1.doubanio.com/view/celebrity/s_ratio_celebrity/public/p45539.webp",
                        "medium": "https://img1.doubanio.com/view/celebrity/s_ratio_celebrity/public/p45539.webp"
                    },
                    "name": "吴君如",
                    "id": "1127819"
                }
            ],
            "year": "2017",
            "images": {
                "small": "https://img3.doubanio.com/view/photo/s_ratio_poster/public/p2506334070.webp",
                "large": "https://img3.doubanio.com/view/photo/s_ratio_poster/public/p2506334070.webp",
                "medium": "https://img3.doubanio.com/view/photo/s_ratio_poster/public/p2506334070.webp"
            },
            "alt": "https://movie.douban.com/subject/26966580/",
            "id": "26966580"
        },
        {
            "rating": {
                "max": 10,
                "average": 0,
                "stars": "00",
                "min": 0
            },
            "genres": [
                "喜剧",
                "爱情",
                "奇幻"
            ],
            "title": "二代妖精之今生有幸",
            "casts": [
                {
                    "alt": "https://movie.douban.com/celebrity/1275721/",
                    "avatars": {
                        "small": "https://img3.doubanio.com/view/celebrity/s_ratio_celebrity/public/p36925.webp",
                        "large": "https://img3.doubanio.com/view/celebrity/s_ratio_celebrity/public/p36925.webp",
                        "medium": "https://img3.doubanio.com/view/celebrity/s_ratio_celebrity/public/p36925.webp"
                    },
                    "name": "冯绍峰",
                    "id": "1275721"
                },
                {
                    "alt": "https://movie.douban.com/celebrity/1049732/",
                    "avatars": {
                        "small": "https://img3.doubanio.com/view/celebrity/s_ratio_celebrity/public/p1513067217.13.webp",
                        "large": "https://img3.doubanio.com/view/celebrity/s_ratio_celebrity/public/p1513067217.13.webp",
                        "medium": "https://img3.doubanio.com/view/celebrity/s_ratio_celebrity/public/p1513067217.13.webp"
                    },
                    "name": "刘亦菲",
                    "id": "1049732"
                },
                {
                    "alt": "https://movie.douban.com/celebrity/1275178/",
                    "avatars": {
                        "small": "https://img3.doubanio.com/view/celebrity/s_ratio_celebrity/public/p37722.webp",
                        "large": "https://img3.doubanio.com/view/celebrity/s_ratio_celebrity/public/p37722.webp",
                        "medium": "https://img3.doubanio.com/view/celebrity/s_ratio_celebrity/public/p37722.webp"
                    },
                    "name": "李光洁",
                    "id": "1275178"
                }
            ],
            "collect_count": 185,
            "original_title": "二代妖精之今生有幸",
            "subtype": "movie",
            "directors": [
                {
                    "alt": "https://movie.douban.com/celebrity/1331182/",
                    "avatars": {
                        "small": "https://img1.doubanio.com/view/celebrity/s_ratio_celebrity/public/p1426816047.48.webp",
                        "large": "https://img1.doubanio.com/view/celebrity/s_ratio_celebrity/public/p1426816047.48.webp",
                        "medium": "https://img1.doubanio.com/view/celebrity/s_ratio_celebrity/public/p1426816047.48.webp"
                    },
                    "name": "肖洋",
                    "id": "1331182"
                }
            ],
            "year": "2017",
            "images": {
                "small": "https://img1.doubanio.com/view/photo/s_ratio_poster/public/p2507022339.webp",
                "large": "https://img1.doubanio.com/view/photo/s_ratio_poster/public/p2507022339.webp",
                "medium": "https://img1.doubanio.com/view/photo/s_ratio_poster/public/p2507022339.webp"
            },
            "alt": "https://movie.douban.com/subject/26797419/",
            "id": "26797419"
        },
        {
            "rating": {
                "max": 10,
                "average": 0,
                "stars": "00",
                "min": 0
            },
            "genres": [
                "喜剧",
                "爱情"
            ],
            "title": "前任3：再见前任",
            "casts": [
                {
                    "alt": "https://movie.douban.com/celebrity/1275667/",
                    "avatars": {
                        "small": "https://img3.doubanio.com/view/celebrity/s_ratio_celebrity/public/p14025.webp",
                        "large": "https://img3.doubanio.com/view/celebrity/s_ratio_celebrity/public/p14025.webp",
                        "medium": "https://img3.doubanio.com/view/celebrity/s_ratio_celebrity/public/p14025.webp"
                    },
                    "name": "韩庚",
                    "id": "1275667"
                },
                {
                    "alt": "https://movie.douban.com/celebrity/1275564/",
                    "avatars": {
                        "small": "https://img3.doubanio.com/view/celebrity/s_ratio_celebrity/public/p1366015827.84.webp",
                        "large": "https://img3.doubanio.com/view/celebrity/s_ratio_celebrity/public/p1366015827.84.webp",
                        "medium": "https://img3.doubanio.com/view/celebrity/s_ratio_celebrity/public/p1366015827.84.webp"
                    },
                    "name": "郑恺",
                    "id": "1275564"
                },
                {
                    "alt": "https://movie.douban.com/celebrity/1342252/",
                    "avatars": {
                        "small": "https://img1.doubanio.com/view/celebrity/s_ratio_celebrity/public/p1408089064.98.webp",
                        "large": "https://img1.doubanio.com/view/celebrity/s_ratio_celebrity/public/p1408089064.98.webp",
                        "medium": "https://img1.doubanio.com/view/celebrity/s_ratio_celebrity/public/p1408089064.98.webp"
                    },
                    "name": "于文文",
                    "id": "1342252"
                }
            ],
            "collect_count": 139,
            "original_title": "前任3：再见前任",
            "subtype": "movie",
            "directors": [
                {
                    "alt": "https://movie.douban.com/celebrity/1332171/",
                    "avatars": {
                        "small": "https://img3.doubanio.com/view/celebrity/s_ratio_celebrity/public/p1391439365.41.webp",
                        "large": "https://img3.doubanio.com/view/celebrity/s_ratio_celebrity/public/p1391439365.41.webp",
                        "medium": "https://img3.doubanio.com/view/celebrity/s_ratio_celebrity/public/p1391439365.41.webp"
                    },
                    "name": "田羽生",
                    "id": "1332171"
                }
            ],
            "year": "2017",
            "images": {
                "small": "https://img3.doubanio.com/view/photo/s_ratio_poster/public/p2506827594.webp",
                "large": "https://img3.doubanio.com/view/photo/s_ratio_poster/public/p2506827594.webp",
                "medium": "https://img3.doubanio.com/view/photo/s_ratio_poster/public/p2506827594.webp"
            },
            "alt": "https://movie.douban.com/subject/26662193/",
            "id": "26662193"
        },
        {
            "rating": {
                "max": 10,
                "average": 0,
                "stars": "00",
                "min": 0
            },
            "genres": [
                "剧情",
                "传记",
                "历史"
            ],
            "title": "我的老兵爷爷",
            "casts": [
                {
                    "alt": "https://movie.douban.com/celebrity/1313235/",
                    "avatars": {
                        "small": "https://img3.doubanio.com/view/celebrity/s_ratio_celebrity/public/p51184.webp",
                        "large": "https://img3.doubanio.com/view/celebrity/s_ratio_celebrity/public/p51184.webp",
                        "medium": "https://img3.doubanio.com/view/celebrity/s_ratio_celebrity/public/p51184.webp"
                    },
                    "name": "许还山",
                    "id": "1313235"
                },
                {
                    "alt": "https://movie.douban.com/celebrity/1323524/",
                    "avatars": {
                        "small": "https://img3.doubanio.com/view/celebrity/s_ratio_celebrity/public/p1369234038.74.webp",
                        "large": "https://img3.doubanio.com/view/celebrity/s_ratio_celebrity/public/p1369234038.74.webp",
                        "medium": "https://img3.doubanio.com/view/celebrity/s_ratio_celebrity/public/p1369234038.74.webp"
                    },
                    "name": "王良",
                    "id": "1323524"
                },
                {
                    "alt": "https://movie.douban.com/celebrity/1275600/",
                    "avatars": {
                        "small": "https://img3.doubanio.com/view/celebrity/s_ratio_celebrity/public/p11524.webp",
                        "large": "https://img3.doubanio.com/view/celebrity/s_ratio_celebrity/public/p11524.webp",
                        "medium": "https://img3.doubanio.com/view/celebrity/s_ratio_celebrity/public/p11524.webp"
                    },
                    "name": "那威",
                    "id": "1275600"
                }
            ],
            "collect_count": 13,
            "original_title": "我的老兵爷爷",
            "subtype": "movie",
            "directors": [
                {
                    "alt": "https://movie.douban.com/celebrity/1323524/",
                    "avatars": {
                        "small": "https://img3.doubanio.com/view/celebrity/s_ratio_celebrity/public/p1369234038.74.webp",
                        "large": "https://img3.doubanio.com/view/celebrity/s_ratio_celebrity/public/p1369234038.74.webp",
                        "medium": "https://img3.doubanio.com/view/celebrity/s_ratio_celebrity/public/p1369234038.74.webp"
                    },
                    "name": "王良",
                    "id": "1323524"
                }
            ],
            "year": "2017",
            "images": {
                "small": "https://img3.doubanio.com/view/photo/s_ratio_poster/public/p2497201336.webp",
                "large": "https://img3.doubanio.com/view/photo/s_ratio_poster/public/p2497201336.webp",
                "medium": "https://img3.doubanio.com/view/photo/s_ratio_poster/public/p2497201336.webp"
            },
            "alt": "https://movie.douban.com/subject/27085629/",
            "id": "27085629"
        },
        {
            "rating": {
                "max": 10,
                "average": 5,
                "stars": "25",
                "min": 0
            },
            "genres": [
                "剧情"
            ],
            "title": "咖啡风暴",
            "casts": [
                {
                    "alt": "https://movie.douban.com/celebrity/1083010/",
                    "avatars": {
                        "small": "https://img1.doubanio.com/view/celebrity/s_ratio_celebrity/public/p21789.webp",
                        "large": "https://img1.doubanio.com/view/celebrity/s_ratio_celebrity/public/p21789.webp",
                        "medium": "https://img1.doubanio.com/view/celebrity/s_ratio_celebrity/public/p21789.webp"
                    },
                    "name": "恩尼奥·凡塔斯蒂基尼",
                    "id": "1083010"
                },
                {
                    "alt": "https://movie.douban.com/celebrity/1315585/",
                    "avatars": {
                        "small": "https://img3.doubanio.com/view/celebrity/s_ratio_celebrity/public/p1380440677.6.webp",
                        "large": "https://img3.doubanio.com/view/celebrity/s_ratio_celebrity/public/p1380440677.6.webp",
                        "medium": "https://img3.doubanio.com/view/celebrity/s_ratio_celebrity/public/p1380440677.6.webp"
                    },
                    "name": "芦芳生",
                    "id": "1315585"
                },
                {
                    "alt": "https://movie.douban.com/celebrity/1312976/",
                    "avatars": {
                        "small": "https://img3.doubanio.com/view/celebrity/s_ratio_celebrity/public/p38291.webp",
                        "large": "https://img3.doubanio.com/view/celebrity/s_ratio_celebrity/public/p38291.webp",
                        "medium": "https://img3.doubanio.com/view/celebrity/s_ratio_celebrity/public/p38291.webp"
                    },
                    "name": "谭卓",
                    "id": "1312976"
                }
            ],
            "collect_count": 44,
            "original_title": "Caffè",
            "subtype": "movie",
            "directors": [
                {
                    "alt": "https://movie.douban.com/celebrity/1010292/",
                    "avatars": {
                        "small": "https://img3.doubanio.com/view/celebrity/s_ratio_celebrity/public/p24213.webp",
                        "large": "https://img3.doubanio.com/view/celebrity/s_ratio_celebrity/public/p24213.webp",
                        "medium": "https://img3.doubanio.com/view/celebrity/s_ratio_celebrity/public/p24213.webp"
                    },
                    "name": "克里斯蒂亚诺·博尔托内",
                    "id": "1010292"
                }
            ],
            "year": "2016",
            "images": {
                "small": "https://img1.doubanio.com/view/photo/s_ratio_poster/public/p2508258787.webp",
                "large": "https://img1.doubanio.com/view/photo/s_ratio_poster/public/p2508258787.webp",
                "medium": "https://img1.doubanio.com/view/photo/s_ratio_poster/public/p2508258787.webp"
            },
            "alt": "https://movie.douban.com/subject/26649225/",
            "id": "26649225"
        },
        {
            "rating": {
                "max": 10,
                "average": 0,
                "stars": "00",
                "min": 0
            },
            "genres": [
                "儿童",
                "动画",
                "奇幻"
            ],
            "title": "小猫巴克里",
            "casts": [
                {
                    "alt": "https://movie.douban.com/celebrity/1386018/",
                    "avatars": {
                        "small": "https://img1.doubanio.com/f/movie/ca527386eb8c4e325611e22dfcb04cc116d6b423/pics/movie/celebrity-default-small.png",
                        "large": "https://img3.doubanio.com/f/movie/63acc16ca6309ef191f0378faf793d1096a3e606/pics/movie/celebrity-default-large.png",
                        "medium": "https://img1.doubanio.com/f/movie/8dd0c794499fe925ae2ae89ee30cd225750457b4/pics/movie/celebrity-default-medium.png"
                    },
                    "name": "林佑俽",
                    "id": "1386018"
                },
                {
                    "alt": "https://movie.douban.com/celebrity/1386019/",
                    "avatars": {
                        "small": "https://img1.doubanio.com/f/movie/ca527386eb8c4e325611e22dfcb04cc116d6b423/pics/movie/celebrity-default-small.png",
                        "large": "https://img3.doubanio.com/f/movie/63acc16ca6309ef191f0378faf793d1096a3e606/pics/movie/celebrity-default-large.png",
                        "medium": "https://img1.doubanio.com/f/movie/8dd0c794499fe925ae2ae89ee30cd225750457b4/pics/movie/celebrity-default-medium.png"
                    },
                    "name": "郭馨雅",
                    "id": "1386019"
                },
                {
                    "alt": "https://movie.douban.com/celebrity/1275593/",
                    "avatars": {
                        "small": "https://img3.doubanio.com/view/celebrity/s_ratio_celebrity/public/p35136.webp",
                        "large": "https://img3.doubanio.com/view/celebrity/s_ratio_celebrity/public/p35136.webp",
                        "medium": "https://img3.doubanio.com/view/celebrity/s_ratio_celebrity/public/p35136.webp"
                    },
                    "name": "屈中恒",
                    "id": "1275593"
                }
            ],
            "collect_count": 9,
            "original_title": "小貓巴克里",
            "subtype": "movie",
            "directors": [
                {
                    "alt": "https://movie.douban.com/celebrity/1372804/",
                    "avatars": {
                        "small": "https://img3.doubanio.com/view/celebrity/s_ratio_celebrity/public/p1512959486.04.webp",
                        "large": "https://img3.doubanio.com/view/celebrity/s_ratio_celebrity/public/p1512959486.04.webp",
                        "medium": "https://img3.doubanio.com/view/celebrity/s_ratio_celebrity/public/p1512959486.04.webp"
                    },
                    "name": "邱立伟",
                    "id": "1372804"
                }
            ],
            "year": "2017",
            "images": {
                "small": "https://img3.doubanio.com/view/photo/s_ratio_poster/public/p2507477603.webp",
                "large": "https://img3.doubanio.com/view/photo/s_ratio_poster/public/p2507477603.webp",
                "medium": "https://img3.doubanio.com/view/photo/s_ratio_poster/public/p2507477603.webp"
            },
            "alt": "https://movie.douban.com/subject/26887161/",
            "id": "26887161"
        },
        {
            "rating": {
                "max": 10,
                "average": 0,
                "stars": "00",
                "min": 0
            },
            "genres": [
                "儿童",
                "动画",
                "奇幻"
            ],
            "title": "咕噜咕噜美人鱼2",
            "casts": [
                {
                    "alt": null,
                    "avatars": null,
                    "name": "丁莹莹",
                    "id": null
                },
                {
                    "alt": null,
                    "avatars": null,
                    "name": "杨  进",
                    "id": null
                },
                {
                    "alt": null,
                    "avatars": null,
                    "name": "卢  瑶",
                    "id": null
                }
            ],
            "collect_count": 1,
            "original_title": "咕噜咕噜美人鱼2",
            "subtype": "movie",
            "directors": [
                {
                    "alt": "https://movie.douban.com/celebrity/1340240/",
                    "avatars": {
                        "small": "https://img3.doubanio.com/view/celebrity/s_ratio_celebrity/public/p1483596470.52.webp",
                        "large": "https://img3.doubanio.com/view/celebrity/s_ratio_celebrity/public/p1483596470.52.webp",
                        "medium": "https://img3.doubanio.com/view/celebrity/s_ratio_celebrity/public/p1483596470.52.webp"
                    },
                    "name": "杨广福",
                    "id": "1340240"
                }
            ],
            "year": "2017",
            "images": {
                "small": "https://img3.doubanio.com/view/photo/s_ratio_poster/public/p2508071436.webp",
                "large": "https://img3.doubanio.com/view/photo/s_ratio_poster/public/p2508071436.webp",
                "medium": "https://img3.doubanio.com/view/photo/s_ratio_poster/public/p2508071436.webp"
            },
            "alt": "https://movie.douban.com/subject/27193475/",
            "id": "27193475"
        },
        {
            "rating": {
                "max": 10,
                "average": 7.6,
                "stars": "40",
                "min": 0
            },
            "genres": [
                "动作",
                "科幻",
                "冒险"
            ],
            "title": "星球大战8：最后的绝地武士",
            "casts": [
                {
                    "alt": "https://movie.douban.com/celebrity/1339916/",
                    "avatars": {
                        "small": "https://img1.doubanio.com/view/celebrity/s_ratio_celebrity/public/p1444659264.8.webp",
                        "large": "https://img1.doubanio.com/view/celebrity/s_ratio_celebrity/public/p1444659264.8.webp",
                        "medium": "https://img1.doubanio.com/view/celebrity/s_ratio_celebrity/public/p1444659264.8.webp"
                    },
                    "name": "黛西·雷德利",
                    "id": "1339916"
                },
                {
                    "alt": "https://movie.douban.com/celebrity/1339915/",
                    "avatars": {
                        "small": "https://img1.doubanio.com/view/celebrity/s_ratio_celebrity/public/p1402281418.08.webp",
                        "large": "https://img1.doubanio.com/view/celebrity/s_ratio_celebrity/public/p1402281418.08.webp",
                        "medium": "https://img1.doubanio.com/view/celebrity/s_ratio_celebrity/public/p1402281418.08.webp"
                    },
                    "name": "约翰·博耶加",
                    "id": "1339915"
                },
                {
                    "alt": "https://movie.douban.com/celebrity/1322327/",
                    "avatars": {
                        "small": "https://img3.doubanio.com/view/celebrity/s_ratio_celebrity/public/p1452758257.45.webp",
                        "large": "https://img3.doubanio.com/view/celebrity/s_ratio_celebrity/public/p1452758257.45.webp",
                        "medium": "https://img3.doubanio.com/view/celebrity/s_ratio_celebrity/public/p1452758257.45.webp"
                    },
                    "name": "亚当·德赖弗",
                    "id": "1322327"
                }
            ],
            "collect_count": 3550,
            "original_title": "Star Wars: The Last Jedi",
            "subtype": "movie",
            "directors": [
                {
                    "alt": "https://movie.douban.com/celebrity/1036605/",
                    "avatars": {
                        "small": "https://img1.doubanio.com/view/celebrity/s_ratio_celebrity/public/p55599.webp",
                        "large": "https://img1.doubanio.com/view/celebrity/s_ratio_celebrity/public/p55599.webp",
                        "medium": "https://img1.doubanio.com/view/celebrity/s_ratio_celebrity/public/p55599.webp"
                    },
                    "name": "莱恩·约翰逊",
                    "id": "1036605"
                }
            ],
            "year": "2017",
            "images": {
                "small": "https://img1.doubanio.com/view/photo/s_ratio_poster/public/p2506694509.webp",
                "large": "https://img1.doubanio.com/view/photo/s_ratio_poster/public/p2506694509.webp",
                "medium": "https://img1.doubanio.com/view/photo/s_ratio_poster/public/p2506694509.webp"
            },
            "alt": "https://movie.douban.com/subject/22265634/",
            "id": "22265634"
        },
        {
            "rating": {
                "max": 10,
                "average": 0,
                "stars": "00",
                "min": 0
            },
            "genres": [
                "剧情"
            ],
            "title": "醉佳导演",
            "casts": [
                {
                    "alt": "https://movie.douban.com/celebrity/1270178/",
                    "avatars": {
                        "small": "https://img1.doubanio.com/view/celebrity/s_ratio_celebrity/public/p11679.webp",
                        "large": "https://img1.doubanio.com/view/celebrity/s_ratio_celebrity/public/p11679.webp",
                        "medium": "https://img1.doubanio.com/view/celebrity/s_ratio_celebrity/public/p11679.webp"
                    },
                    "name": "贺军翔",
                    "id": "1270178"
                },
                {
                    "alt": "https://movie.douban.com/celebrity/1275719/",
                    "avatars": {
                        "small": "https://img3.doubanio.com/view/celebrity/s_ratio_celebrity/public/p33404.webp",
                        "large": "https://img3.doubanio.com/view/celebrity/s_ratio_celebrity/public/p33404.webp",
                        "medium": "https://img3.doubanio.com/view/celebrity/s_ratio_celebrity/public/p33404.webp"
                    },
                    "name": "江若琳",
                    "id": "1275719"
                },
                {
                    "alt": "https://movie.douban.com/celebrity/1344481/",
                    "avatars": {
                        "small": "https://img3.doubanio.com/view/celebrity/s_ratio_celebrity/public/p1420960154.24.webp",
                        "large": "https://img3.doubanio.com/view/celebrity/s_ratio_celebrity/public/p1420960154.24.webp",
                        "medium": "https://img3.doubanio.com/view/celebrity/s_ratio_celebrity/public/p1420960154.24.webp"
                    },
                    "name": "刘宇",
                    "id": "1344481"
                }
            ],
            "collect_count": 18,
            "original_title": "醉佳导演",
            "subtype": "movie",
            "directors": [
                {
                    "alt": "https://movie.douban.com/celebrity/1376585/",
                    "avatars": {
                        "small": "https://img1.doubanio.com/view/celebrity/s_ratio_celebrity/public/p1512046051.59.webp",
                        "large": "https://img1.doubanio.com/view/celebrity/s_ratio_celebrity/public/p1512046051.59.webp",
                        "medium": "https://img1.doubanio.com/view/celebrity/s_ratio_celebrity/public/p1512046051.59.webp"
                    },
                    "name": "武圣基",
                    "id": "1376585"
                }
            ],
            "year": "2018",
            "images": {
                "small": "https://img3.doubanio.com/view/photo/s_ratio_poster/public/p2483549935.webp",
                "large": "https://img3.doubanio.com/view/photo/s_ratio_poster/public/p2483549935.webp",
                "medium": "https://img3.doubanio.com/view/photo/s_ratio_poster/public/p2483549935.webp"
            },
            "alt": "https://movie.douban.com/subject/27082927/",
            "id": "27082927"
        },
        {
            "rating": {
                "max": 10,
                "average": 0,
                "stars": "00",
                "min": 0
            },
            "genres": [
                "剧情",
                "爱情"
            ],
            "title": "我来过",
            "casts": [
                {
                    "alt": "https://movie.douban.com/celebrity/1322460/",
                    "avatars": {
                        "small": "https://img3.doubanio.com/view/celebrity/s_ratio_celebrity/public/p1395325623.3.webp",
                        "large": "https://img3.doubanio.com/view/celebrity/s_ratio_celebrity/public/p1395325623.3.webp",
                        "medium": "https://img3.doubanio.com/view/celebrity/s_ratio_celebrity/public/p1395325623.3.webp"
                    },
                    "name": "汪洋",
                    "id": "1322460"
                },
                {
                    "alt": "https://movie.douban.com/celebrity/1330862/",
                    "avatars": {
                        "small": "https://img3.doubanio.com/view/celebrity/s_ratio_celebrity/public/p1372835316.42.webp",
                        "large": "https://img3.doubanio.com/view/celebrity/s_ratio_celebrity/public/p1372835316.42.webp",
                        "medium": "https://img3.doubanio.com/view/celebrity/s_ratio_celebrity/public/p1372835316.42.webp"
                    },
                    "name": "冯铭潮",
                    "id": "1330862"
                },
                {
                    "alt": "https://movie.douban.com/celebrity/1384232/",
                    "avatars": {
                        "small": "https://img1.doubanio.com/f/movie/ca527386eb8c4e325611e22dfcb04cc116d6b423/pics/movie/celebrity-default-small.png",
                        "large": "https://img3.doubanio.com/f/movie/63acc16ca6309ef191f0378faf793d1096a3e606/pics/movie/celebrity-default-large.png",
                        "medium": "https://img1.doubanio.com/f/movie/8dd0c794499fe925ae2ae89ee30cd225750457b4/pics/movie/celebrity-default-medium.png"
                    },
                    "name": "孙映霏",
                    "id": "1384232"
                }
            ],
            "collect_count": 2,
            "original_title": "我来过",
            "subtype": "movie",
            "directors": [
                {
                    "alt": "https://movie.douban.com/celebrity/1384231/",
                    "avatars": {
                        "small": "https://img3.doubanio.com/view/celebrity/s_ratio_celebrity/public/p1511931014.54.webp",
                        "large": "https://img3.doubanio.com/view/celebrity/s_ratio_celebrity/public/p1511931014.54.webp",
                        "medium": "https://img3.doubanio.com/view/celebrity/s_ratio_celebrity/public/p1511931014.54.webp"
                    },
                    "name": "周沫",
                    "id": "1384231"
                }
            ],
            "year": "2018",
            "images": {
                "small": "https://img1.doubanio.com/view/photo/s_ratio_poster/public/p2506261838.webp",
                "large": "https://img1.doubanio.com/view/photo/s_ratio_poster/public/p2506261838.webp",
                "medium": "https://img1.doubanio.com/view/photo/s_ratio_poster/public/p2506261838.webp"
            },
            "alt": "https://movie.douban.com/subject/27199690/",
            "id": "27199690"
        },
        {
            "rating": {
                "max": 10,
                "average": 0,
                "stars": "00",
                "min": 0
            },
            "genres": [
                "剧情",
                "爱情",
                "歌舞"
            ],
            "title": "十七后 与青春化敌为友",
            "casts": [
                {
                    "alt": "https://movie.douban.com/celebrity/1355356/",
                    "avatars": {
                        "small": "https://img1.doubanio.com/view/celebrity/s_ratio_celebrity/public/p1457094385.68.webp",
                        "large": "https://img1.doubanio.com/view/celebrity/s_ratio_celebrity/public/p1457094385.68.webp",
                        "medium": "https://img1.doubanio.com/view/celebrity/s_ratio_celebrity/public/p1457094385.68.webp"
                    },
                    "name": "中泽祥",
                    "id": "1355356"
                },
                {
                    "alt": "https://movie.douban.com/celebrity/1355352/",
                    "avatars": {
                        "small": "https://img1.doubanio.com/view/celebrity/s_ratio_celebrity/public/p1457092978.88.webp",
                        "large": "https://img1.doubanio.com/view/celebrity/s_ratio_celebrity/public/p1457092978.88.webp",
                        "medium": "https://img1.doubanio.com/view/celebrity/s_ratio_celebrity/public/p1457092978.88.webp"
                    },
                    "name": "翁滋蔓",
                    "id": "1355352"
                },
                {
                    "alt": "https://movie.douban.com/celebrity/1384709/",
                    "avatars": {
                        "small": "https://img1.doubanio.com/view/celebrity/s_ratio_celebrity/public/p1511511024.17.webp",
                        "large": "https://img1.doubanio.com/view/celebrity/s_ratio_celebrity/public/p1511511024.17.webp",
                        "medium": "https://img1.doubanio.com/view/celebrity/s_ratio_celebrity/public/p1511511024.17.webp"
                    },
                    "name": "邦邦",
                    "id": "1384709"
                }
            ],
            "collect_count": 27,
            "original_title": "終極舞班",
            "subtype": "movie",
            "directors": [
                {
                    "alt": "https://movie.douban.com/celebrity/1331629/",
                    "avatars": {
                        "small": "https://img1.doubanio.com/view/celebrity/s_ratio_celebrity/public/p1511511192.18.webp",
                        "large": "https://img1.doubanio.com/view/celebrity/s_ratio_celebrity/public/p1511511192.18.webp",
                        "medium": "https://img1.doubanio.com/view/celebrity/s_ratio_celebrity/public/p1511511192.18.webp"
                    },
                    "name": "罗颂其",
                    "id": "1331629"
                }
            ],
            "year": "2016",
            "images": {
                "small": "https://img3.doubanio.com/view/photo/s_ratio_poster/public/p2505793153.webp",
                "large": "https://img3.doubanio.com/view/photo/s_ratio_poster/public/p2505793153.webp",
                "medium": "https://img3.doubanio.com/view/photo/s_ratio_poster/public/p2505793153.webp"
            },
            "alt": "https://movie.douban.com/subject/26731790/",
            "id": "26731790"
        },
        {
            "rating": {
                "max": 10,
                "average": 7.5,
                "stars": "40",
                "min": 0
            },
            "genres": [
                "动画"
            ],
            "title": "大世界",
            "casts": [],
            "collect_count": 1102,
            "original_title": "大世界",
            "subtype": "movie",
            "directors": [
                {
                    "alt": "https://movie.douban.com/celebrity/1275433/",
                    "avatars": {
                        "small": "https://img1.doubanio.com/view/celebrity/s_ratio_celebrity/public/p1484937150.59.webp",
                        "large": "https://img1.doubanio.com/view/celebrity/s_ratio_celebrity/public/p1484937150.59.webp",
                        "medium": "https://img1.doubanio.com/view/celebrity/s_ratio_celebrity/public/p1484937150.59.webp"
                    },
                    "name": "刘健",
                    "id": "1275433"
                }
            ],
            "year": "2017",
            "images": {
                "small": "https://img3.doubanio.com/view/photo/s_ratio_poster/public/p2508258043.webp",
                "large": "https://img3.doubanio.com/view/photo/s_ratio_poster/public/p2508258043.webp",
                "medium": "https://img3.doubanio.com/view/photo/s_ratio_poster/public/p2508258043.webp"
            },
            "alt": "https://movie.douban.com/subject/26954003/",
            "id": "26954003"
        },
        {
            "rating": {
                "max": 10,
                "average": 0,
                "stars": "00",
                "min": 0
            },
            "genres": [
                "剧情",
                "爱情",
                "战争"
            ],
            "title": "无问西东",
            "casts": [
                {
                    "alt": "https://movie.douban.com/celebrity/1041014/",
                    "avatars": {
                        "small": "https://img3.doubanio.com/view/celebrity/s_ratio_celebrity/public/p1359895311.0.webp",
                        "large": "https://img3.doubanio.com/view/celebrity/s_ratio_celebrity/public/p1359895311.0.webp",
                        "medium": "https://img3.doubanio.com/view/celebrity/s_ratio_celebrity/public/p1359895311.0.webp"
                    },
                    "name": "章子怡",
                    "id": "1041014"
                },
                {
                    "alt": "https://movie.douban.com/celebrity/1041404/",
                    "avatars": {
                        "small": "https://img1.doubanio.com/view/celebrity/s_ratio_celebrity/public/p1513837613.88.webp",
                        "large": "https://img1.doubanio.com/view/celebrity/s_ratio_celebrity/public/p1513837613.88.webp",
                        "medium": "https://img1.doubanio.com/view/celebrity/s_ratio_celebrity/public/p1513837613.88.webp"
                    },
                    "name": "黄晓明",
                    "id": "1041404"
                },
                {
                    "alt": "https://movie.douban.com/celebrity/1077991/",
                    "avatars": {
                        "small": "https://img1.doubanio.com/view/celebrity/s_ratio_celebrity/public/p1453574419.48.webp",
                        "large": "https://img1.doubanio.com/view/celebrity/s_ratio_celebrity/public/p1453574419.48.webp",
                        "medium": "https://img1.doubanio.com/view/celebrity/s_ratio_celebrity/public/p1453574419.48.webp"
                    },
                    "name": "张震",
                    "id": "1077991"
                }
            ],
            "collect_count": 161,
            "original_title": "无问西东",
            "subtype": "movie",
            "directors": [
                {
                    "alt": "https://movie.douban.com/celebrity/1313682/",
                    "avatars": {
                        "small": "https://img3.doubanio.com/view/celebrity/s_ratio_celebrity/public/p19485.webp",
                        "large": "https://img3.doubanio.com/view/celebrity/s_ratio_celebrity/public/p19485.webp",
                        "medium": "https://img3.doubanio.com/view/celebrity/s_ratio_celebrity/public/p19485.webp"
                    },
                    "name": "李芳芳",
                    "id": "1313682"
                }
            ],
            "year": "2018",
            "images": {
                "small": "https://img3.doubanio.com/view/photo/s_ratio_poster/public/p2506934926.webp",
                "large": "https://img3.doubanio.com/view/photo/s_ratio_poster/public/p2506934926.webp",
                "medium": "https://img3.doubanio.com/view/photo/s_ratio_poster/public/p2506934926.webp"
            },
            "alt": "https://movie.douban.com/subject/6874741/",
            "id": "6874741"
        },
        {
            "rating": {
                "max": 10,
                "average": 7.7,
                "stars": "40",
                "min": 0
            },
            "genres": [
                "动作",
                "奇幻",
                "冒险"
            ],
            "title": "勇敢者游戏：决战丛林",
            "casts": [
                {
                    "alt": "https://movie.douban.com/celebrity/1044707/",
                    "avatars": {
                        "small": "https://img3.doubanio.com/view/celebrity/s_ratio_celebrity/public/p196.webp",
                        "large": "https://img3.doubanio.com/view/celebrity/s_ratio_celebrity/public/p196.webp",
                        "medium": "https://img3.doubanio.com/view/celebrity/s_ratio_celebrity/public/p196.webp"
                    },
                    "name": "道恩·强森",
                    "id": "1044707"
                },
                {
                    "alt": "https://movie.douban.com/celebrity/1286162/",
                    "avatars": {
                        "small": "https://img3.doubanio.com/view/celebrity/s_ratio_celebrity/public/p56350.webp",
                        "large": "https://img3.doubanio.com/view/celebrity/s_ratio_celebrity/public/p56350.webp",
                        "medium": "https://img3.doubanio.com/view/celebrity/s_ratio_celebrity/public/p56350.webp"
                    },
                    "name": "凯文·哈特",
                    "id": "1286162"
                },
                {
                    "alt": "https://movie.douban.com/celebrity/1049492/",
                    "avatars": {
                        "small": "https://img3.doubanio.com/view/celebrity/s_ratio_celebrity/public/p35722.webp",
                        "large": "https://img3.doubanio.com/view/celebrity/s_ratio_celebrity/public/p35722.webp",
                        "medium": "https://img3.doubanio.com/view/celebrity/s_ratio_celebrity/public/p35722.webp"
                    },
                    "name": "杰克·布莱克",
                    "id": "1049492"
                }
            ],
            "collect_count": 279,
            "original_title": "Jumanji: Welcome to the Jungle",
            "subtype": "movie",
            "directors": [
                {
                    "alt": "https://movie.douban.com/celebrity/1040862/",
                    "avatars": {
                        "small": "https://img1.doubanio.com/view/celebrity/s_ratio_celebrity/public/p14058.webp",
                        "large": "https://img1.doubanio.com/view/celebrity/s_ratio_celebrity/public/p14058.webp",
                        "medium": "https://img1.doubanio.com/view/celebrity/s_ratio_celebrity/public/p14058.webp"
                    },
                    "name": "杰克·卡斯丹",
                    "id": "1040862"
                }
            ],
            "year": "2017",
            "images": {
                "small": "https://img3.doubanio.com/view/photo/s_ratio_poster/public/p2508165594.webp",
                "large": "https://img3.doubanio.com/view/photo/s_ratio_poster/public/p2508165594.webp",
                "medium": "https://img3.doubanio.com/view/photo/s_ratio_poster/public/p2508165594.webp"
            },
            "alt": "https://movie.douban.com/subject/26586766/",
            "id": "26586766"
        },
        {
            "rating": {
                "max": 10,
                "average": 7.3,
                "stars": "40",
                "min": 0
            },
            "genres": [
                "动作",
                "科幻",
                "冒险"
            ],
            "title": "太空救援",
            "casts": [
                {
                    "alt": "https://movie.douban.com/celebrity/1327850/",
                    "avatars": {
                        "small": "https://img3.doubanio.com/view/celebrity/s_ratio_celebrity/public/p1486282779.93.webp",
                        "large": "https://img3.doubanio.com/view/celebrity/s_ratio_celebrity/public/p1486282779.93.webp",
                        "medium": "https://img3.doubanio.com/view/celebrity/s_ratio_celebrity/public/p1486282779.93.webp"
                    },
                    "name": "柳波芙·阿克肖诺娃",
                    "id": "1327850"
                },
                {
                    "alt": "https://movie.douban.com/celebrity/1023442/",
                    "avatars": {
                        "small": "https://img1.doubanio.com/view/celebrity/s_ratio_celebrity/public/p1368685365.9.webp",
                        "large": "https://img1.doubanio.com/view/celebrity/s_ratio_celebrity/public/p1368685365.9.webp",
                        "medium": "https://img1.doubanio.com/view/celebrity/s_ratio_celebrity/public/p1368685365.9.webp"
                    },
                    "name": "弗拉季米尔·弗多维琴科夫",
                    "id": "1023442"
                },
                {
                    "alt": "https://movie.douban.com/celebrity/1194282/",
                    "avatars": {
                        "small": "https://img1.doubanio.com/view/celebrity/s_ratio_celebrity/public/p1416541847.87.webp",
                        "large": "https://img1.doubanio.com/view/celebrity/s_ratio_celebrity/public/p1416541847.87.webp",
                        "medium": "https://img1.doubanio.com/view/celebrity/s_ratio_celebrity/public/p1416541847.87.webp"
                    },
                    "name": "巴维尔·捷列连科",
                    "id": "1194282"
                }
            ],
            "collect_count": 1921,
            "original_title": "Салют-7",
            "subtype": "movie",
            "directors": [
                {
                    "alt": "https://movie.douban.com/celebrity/1382988/",
                    "avatars": {
                        "small": "https://img1.doubanio.com/view/celebrity/s_ratio_celebrity/public/p1511446479.18.webp",
                        "large": "https://img1.doubanio.com/view/celebrity/s_ratio_celebrity/public/p1511446479.18.webp",
                        "medium": "https://img1.doubanio.com/view/celebrity/s_ratio_celebrity/public/p1511446479.18.webp"
                    },
                    "name": "克里姆·斯彭科",
                    "id": "1382988"
                }
            ],
            "year": "2017",
            "images": {
                "small": "https://img1.doubanio.com/view/photo/s_ratio_poster/public/p2507727907.webp",
                "large": "https://img1.doubanio.com/view/photo/s_ratio_poster/public/p2507727907.webp",
                "medium": "https://img1.doubanio.com/view/photo/s_ratio_poster/public/p2507727907.webp"
            },
            "alt": "https://movie.douban.com/subject/27073291/",
            "id": "27073291"
        },
        {
            "rating": {
                "max": 10,
                "average": 0,
                "stars": "00",
                "min": 0
            },
            "genres": [
                "喜剧",
                "动作"
            ],
            "title": "卧底巨星",
            "casts": [
                {
                    "alt": "https://movie.douban.com/celebrity/1023424/",
                    "avatars": {
                        "small": "https://img3.doubanio.com/view/celebrity/s_ratio_celebrity/public/p20210.webp",
                        "large": "https://img3.doubanio.com/view/celebrity/s_ratio_celebrity/public/p20210.webp",
                        "medium": "https://img3.doubanio.com/view/celebrity/s_ratio_celebrity/public/p20210.webp"
                    },
                    "name": "陈奕迅",
                    "id": "1023424"
                },
                {
                    "alt": "https://movie.douban.com/celebrity/1346431/",
                    "avatars": {
                        "small": "https://img3.doubanio.com/view/celebrity/s_ratio_celebrity/public/pMzDHlD0dJgcel_avatar_uploaded1421546376.16.webp",
                        "large": "https://img3.doubanio.com/view/celebrity/s_ratio_celebrity/public/pMzDHlD0dJgcel_avatar_uploaded1421546376.16.webp",
                        "medium": "https://img3.doubanio.com/view/celebrity/s_ratio_celebrity/public/pMzDHlD0dJgcel_avatar_uploaded1421546376.16.webp"
                    },
                    "name": "李荣浩",
                    "id": "1346431"
                },
                {
                    "alt": "https://movie.douban.com/celebrity/1354284/",
                    "avatars": {
                        "small": "https://img3.doubanio.com/view/celebrity/s_ratio_celebrity/public/p1465192722.92.webp",
                        "large": "https://img3.doubanio.com/view/celebrity/s_ratio_celebrity/public/p1465192722.92.webp",
                        "medium": "https://img3.doubanio.com/view/celebrity/s_ratio_celebrity/public/p1465192722.92.webp"
                    },
                    "name": "李一桐",
                    "id": "1354284"
                }
            ],
            "collect_count": 10,
            "original_title": "卧底巨星",
            "subtype": "movie",
            "directors": [
                {
                    "alt": "https://movie.douban.com/celebrity/1025526/",
                    "avatars": {
                        "small": "https://img1.doubanio.com/view/celebrity/s_ratio_celebrity/public/p1057.webp",
                        "large": "https://img1.doubanio.com/view/celebrity/s_ratio_celebrity/public/p1057.webp",
                        "medium": "https://img1.doubanio.com/view/celebrity/s_ratio_celebrity/public/p1057.webp"
                    },
                    "name": "谷德昭",
                    "id": "1025526"
                }
            ],
            "year": "2018",
            "images": {
                "small": "https://img3.doubanio.com/view/photo/s_ratio_poster/public/p2506409872.webp",
                "large": "https://img3.doubanio.com/view/photo/s_ratio_poster/public/p2506409872.webp",
                "medium": "https://img3.doubanio.com/view/photo/s_ratio_poster/public/p2506409872.webp"
            },
            "alt": "https://movie.douban.com/subject/26984538/",
            "id": "26984538"
        },
        {
            "rating": {
                "max": 10,
                "average": 0,
                "stars": "00",
                "min": 0
            },
            "genres": [
                "科幻",
                "悬疑"
            ],
            "title": "时空终点",
            "casts": [
                {
                    "alt": "https://movie.douban.com/celebrity/1384525/",
                    "avatars": {
                        "small": "https://img3.doubanio.com/view/celebrity/s_ratio_celebrity/public/p1511344644.35.webp",
                        "large": "https://img3.doubanio.com/view/celebrity/s_ratio_celebrity/public/p1511344644.35.webp",
                        "medium": "https://img3.doubanio.com/view/celebrity/s_ratio_celebrity/public/p1511344644.35.webp"
                    },
                    "name": "欧阳佳",
                    "id": "1384525"
                },
                {
                    "alt": "https://movie.douban.com/celebrity/1340961/",
                    "avatars": {
                        "small": "https://img3.doubanio.com/view/celebrity/s_ratio_celebrity/public/p1511344691.21.webp",
                        "large": "https://img3.doubanio.com/view/celebrity/s_ratio_celebrity/public/p1511344691.21.webp",
                        "medium": "https://img3.doubanio.com/view/celebrity/s_ratio_celebrity/public/p1511344691.21.webp"
                    },
                    "name": "高翔",
                    "id": "1340961"
                },
                {
                    "alt": "https://movie.douban.com/celebrity/1318405/",
                    "avatars": {
                        "small": "https://img1.doubanio.com/view/celebrity/s_ratio_celebrity/public/p57349.webp",
                        "large": "https://img1.doubanio.com/view/celebrity/s_ratio_celebrity/public/p57349.webp",
                        "medium": "https://img1.doubanio.com/view/celebrity/s_ratio_celebrity/public/p57349.webp"
                    },
                    "name": "雷诺儿",
                    "id": "1318405"
                }
            ],
            "collect_count": 3,
            "original_title": "时空终点",
            "subtype": "movie",
            "directors": [
                {
                    "alt": "https://movie.douban.com/celebrity/1343046/",
                    "avatars": {
                        "small": "https://img1.doubanio.com/view/celebrity/s_ratio_celebrity/public/p1481636086.27.webp",
                        "large": "https://img1.doubanio.com/view/celebrity/s_ratio_celebrity/public/p1481636086.27.webp",
                        "medium": "https://img1.doubanio.com/view/celebrity/s_ratio_celebrity/public/p1481636086.27.webp"
                    },
                    "name": "叶小舟",
                    "id": "1343046"
                }
            ],
            "year": "2018",
            "images": {
                "small": "https://img3.doubanio.com/view/photo/s_ratio_poster/public/p2507458273.webp",
                "large": "https://img3.doubanio.com/view/photo/s_ratio_poster/public/p2507458273.webp",
                "medium": "https://img3.doubanio.com/view/photo/s_ratio_poster/public/p2507458273.webp"
            },
            "alt": "https://movie.douban.com/subject/27199679/",
            "id": "27199679"
        },
        {
            "rating": {
                "max": 10,
                "average": 3.5,
                "stars": "20",
                "min": 0
            },
            "genres": [
                "喜剧",
                "动画"
            ],
            "title": "青蛙总动员",
            "casts": [
                {
                    "alt": "https://movie.douban.com/celebrity/1355838/",
                    "avatars": {
                        "small": "https://img1.doubanio.com/f/movie/ca527386eb8c4e325611e22dfcb04cc116d6b423/pics/movie/celebrity-default-small.png",
                        "large": "https://img3.doubanio.com/f/movie/63acc16ca6309ef191f0378faf793d1096a3e606/pics/movie/celebrity-default-large.png",
                        "medium": "https://img1.doubanio.com/f/movie/8dd0c794499fe925ae2ae89ee30cd225750457b4/pics/movie/celebrity-default-medium.png"
                    },
                    "name": "吉静",
                    "id": "1355838"
                },
                {
                    "alt": "https://movie.douban.com/celebrity/1325740/",
                    "avatars": {
                        "small": "https://img3.doubanio.com/view/celebrity/s_ratio_celebrity/public/p1478051011.64.webp",
                        "large": "https://img3.doubanio.com/view/celebrity/s_ratio_celebrity/public/p1478051011.64.webp",
                        "medium": "https://img3.doubanio.com/view/celebrity/s_ratio_celebrity/public/p1478051011.64.webp"
                    },
                    "name": "郭政建",
                    "id": "1325740"
                },
                {
                    "alt": "https://movie.douban.com/celebrity/1355839/",
                    "avatars": {
                        "small": "https://img1.doubanio.com/view/celebrity/s_ratio_celebrity/public/p1477650538.99.webp",
                        "large": "https://img1.doubanio.com/view/celebrity/s_ratio_celebrity/public/p1477650538.99.webp",
                        "medium": "https://img1.doubanio.com/view/celebrity/s_ratio_celebrity/public/p1477650538.99.webp"
                    },
                    "name": "白涛",
                    "id": "1355839"
                }
            ],
            "collect_count": 561,
            "original_title": "青蛙总动员",
            "subtype": "movie",
            "directors": [
                {
                    "alt": "https://movie.douban.com/celebrity/1356405/",
                    "avatars": {
                        "small": "https://img1.doubanio.com/f/movie/ca527386eb8c4e325611e22dfcb04cc116d6b423/pics/movie/celebrity-default-small.png",
                        "large": "https://img3.doubanio.com/f/movie/63acc16ca6309ef191f0378faf793d1096a3e606/pics/movie/celebrity-default-large.png",
                        "medium": "https://img1.doubanio.com/f/movie/8dd0c794499fe925ae2ae89ee30cd225750457b4/pics/movie/celebrity-default-medium.png"
                    },
                    "name": "杨仁贤",
                    "id": "1356405"
                }
            ],
            "year": "2016",
            "images": {
                "small": "https://img3.doubanio.com/view/photo/s_ratio_poster/public/p2508255304.webp",
                "large": "https://img3.doubanio.com/view/photo/s_ratio_poster/public/p2508255304.webp",
                "medium": "https://img3.doubanio.com/view/photo/s_ratio_poster/public/p2508255304.webp"
            },
            "alt": "https://movie.douban.com/subject/26752895/",
            "id": "26752895"
        },
        {
            "rating": {
                "max": 10,
                "average": 7.1,
                "stars": "35",
                "min": 0
            },
            "genres": [
                "剧情",
                "儿童",
                "家庭"
            ],
            "title": "我的影子在奔跑",
            "casts": [
                {
                    "alt": "https://movie.douban.com/celebrity/1016668/",
                    "avatars": {
                        "small": "https://img3.doubanio.com/view/celebrity/s_ratio_celebrity/public/p146.webp",
                        "large": "https://img3.doubanio.com/view/celebrity/s_ratio_celebrity/public/p146.webp",
                        "medium": "https://img3.doubanio.com/view/celebrity/s_ratio_celebrity/public/p146.webp"
                    },
                    "name": "张静初",
                    "id": "1016668"
                },
                {
                    "alt": "https://movie.douban.com/celebrity/1330245/",
                    "avatars": {
                        "small": "https://img3.doubanio.com/view/celebrity/s_ratio_celebrity/public/p1371455504.24.webp",
                        "large": "https://img3.doubanio.com/view/celebrity/s_ratio_celebrity/public/p1371455504.24.webp",
                        "medium": "https://img3.doubanio.com/view/celebrity/s_ratio_celebrity/public/p1371455504.24.webp"
                    },
                    "name": "龙品旭",
                    "id": "1330245"
                },
                {
                    "alt": "https://movie.douban.com/celebrity/1331753/",
                    "avatars": {
                        "small": "https://img1.doubanio.com/f/movie/ca527386eb8c4e325611e22dfcb04cc116d6b423/pics/movie/celebrity-default-small.png",
                        "large": "https://img3.doubanio.com/f/movie/63acc16ca6309ef191f0378faf793d1096a3e606/pics/movie/celebrity-default-large.png",
                        "medium": "https://img1.doubanio.com/f/movie/8dd0c794499fe925ae2ae89ee30cd225750457b4/pics/movie/celebrity-default-medium.png"
                    },
                    "name": "黎兆丰",
                    "id": "1331753"
                }
            ],
            "collect_count": 374,
            "original_title": "我的影子在奔跑",
            "subtype": "movie",
            "directors": [
                {
                    "alt": "https://movie.douban.com/celebrity/1309562/",
                    "avatars": {
                        "small": "https://img3.doubanio.com/view/celebrity/s_ratio_celebrity/public/p25505.webp",
                        "large": "https://img3.doubanio.com/view/celebrity/s_ratio_celebrity/public/p25505.webp",
                        "medium": "https://img3.doubanio.com/view/celebrity/s_ratio_celebrity/public/p25505.webp"
                    },
                    "name": "方刚亮",
                    "id": "1309562"
                }
            ],
            "year": "2013",
            "images": {
                "small": "https://img3.doubanio.com/view/photo/s_ratio_poster/public/p2508256074.webp",
                "large": "https://img3.doubanio.com/view/photo/s_ratio_poster/public/p2508256074.webp",
                "medium": "https://img3.doubanio.com/view/photo/s_ratio_poster/public/p2508256074.webp"
            },
            "alt": "https://movie.douban.com/subject/11615929/",
            "id": "11615929"
        }
    ],
    "title": "即将上映的电影"
}